tornado_router/__init__.py
tornado_router/demo.py
tornado_router/web.py
tornado_router/test/__init__.py
tornado_router/test/web_test.py
tor_router-0.0.3.dist-info/LICENSE
tor_router-0.0.3.dist-info/METADATA
tor_router-0.0.3.dist-info/WHEEL
tor_router-0.0.3.dist-info/top_level.txt
tor_router-0.0.3.dist-info/RECORD
