Metadata-Version: 2.1
Name: tor-router
Version: 0.0.3
Summary: make routing similar to flask blueprint
Home-page: https://github.com/whales2018/Tornado_Router
Author: Whales Zhong
Author-email: whaleszhong@gmail.com
License: UNKNOWN
Platform: UNKNOWN
Classifier: Programming Language :: Python :: 2
Classifier: License :: OSI Approved :: MIT License
Classifier: Operating System :: OS Independent
